{
 "version": 1,
 "runs": 3,
 "vocab": "e47ef807e507",
 "updated_utc": "2026-07-03T01:48:19.362Z",
 "entries": {
  "https://study.csu.edu.au/international/how-to-apply/course-entry-requirements": {
   "row": {
    "university": "charley",
    "country": "Australia",
    "level": "university",
    "course_name": "",
    "url": "https://study.csu.edu.au/international/apply/course-entry-requirements",
    "final_url": "https://study.csu.edu.au/international/how-to-apply/course-entry-requirements",
    "http_status": 200,
    "validity": "WORKING",
    "link_id": "cmr383h1709evj6vewmc4m9qu"
   },
   "misses": 0,
   "last_confirmed_utc": "2026-07-03T01:48:19.362Z"
  }
 }
}